[
    {
        "firstname": "Sagor",
        "lastname": "Sagor",
        "age": "23",
        "designation:": "S_pro",
        "mail": "sagor23@gmail.com",
        "password": "asdfasdfasdfasd333",
        "FILE": ""
    },
    {
        "firstname": "Sagor",
        "lastname": "Sagor",
        "age": "23",
        "designation:": "J_pro",
        "mail": "sagor23@gmail.com",
        "password": "Amiaskldjfhasklj3333",
        "FILE": ""
    },
    {
        "firstname": "Sagor",
        "lastname": "Sagor",
        "age": "23",
        "designation:": "S_pro",
        "mail": "sagor23@gmail.com",
        "password": "asdfjasldfjalsdfjkljasdjkh333",
        "FILE": ""
    },
    {
        "firstname": "Sagor",
        "lastname": "Sagor",
        "age": "23",
        "designation:": "S_pro",
        "mail": "sagor23@gmail.com",
        "password": "asdfasdfasdf3333",
        "FILE": ""
    },
    {
        "firstname": "Sagor",
        "lastname": "Sagor",
        "age": "23",
        "designation:": "S_pro",
        "mail": "sagor23@gmail.com",
        "password": "asdfsfzasdfa333",
        "FILE": ""
    },
    {
        "firstname": "",
        "lastname": "",
        "age": "",
        "designation:": null,
        "mail": "",
        "password": "",
        "FILE": ""
    },
    {
        "firstname": "Sagor",
        "lastname": "Sagor",
        "age": "23",
        "designation:": "S_pro",
        "mail": "sagor23@gmail.com",
        "password": "asdfasdfasasdf3333",
        "FILE": ""
    },
    {
        "firstname": "Sagor",
        "lastname": "Sagor",
        "age": "23",
        "designation:": "S_pro",
        "mail": "sagor23@gmail.com",
        "password": "asdfasdfasdfasdf3",
        "FILE": ""
    },
    {
        "firstname": "Sagor",
        "lastname": "Sagor",
        "age": "23",
        "designation:": "S_pro",
        "mail": "sagor23@gmail.com",
        "password": "asdfasdfasd2",
        "FILE": ""
    },
    {
        "firstname": "Sagor",
        "lastname": "Sagor",
        "age": "23",
        "designation:": "S_pro",
        "mail": "sagor23@gmail.com",
        "password": "asdfasdfas3",
        "FILE": ""
    },
    {
        "firstname": "Sagor",
        "lastname": "Sagor",
        "age": "23",
        "designation:": "S_pro",
        "mail": "sagor23@gmail.com",
        "password": "asdfoiasdhfoahsdfjkah333",
        "FILE": ""
    },
    {
        "firstname": "Sagor",
        "lastname": "Sagor",
        "age": "22",
        "designation:": "J_pro",
        "mail": "sagor23@gmail.com",
        "password": "ydujhcjydudyxh",
        "FILE": ""
    },
    {
        "firstname": "Sagor",
        "lastname": "Sagor",
        "age": "22",
        "designation:": "S_pro",
        "mail": "sagor23@gmail.com",
        "password": "HTDHDHDTYUF",
        "FILE": ""
    }
]